[
  {
    "uri": "features/specs/add_to_cart.feature",
    "id": "add-a-product-to-cart",
    "keyword": "Feature",
    "name": "Add a product to cart",
    "description": "  As a customer of the website\n  I want to add products to my cart\n  To proceed to checkout and buy all of them at once",
    "line": 1,
    "elements": [
      {
        "keyword": "Background",
        "name": "",
        "description": "",
        "line": 6,
        "type": "background",
        "before": [
          {
            "match": {
              "location": "capybara-3.29.0/lib/capybara/cucumber.rb:14"
            },
            "result": {
              "status": "passed",
              "duration": 26800
            }
          },
          {
            "match": {
              "location": "capybara-3.29.0/lib/capybara/cucumber.rb:22"
            },
            "result": {
              "status": "passed",
              "duration": 12400
            }
          },
          {
            "match": {
              "location": "features/support/hooks.rb:1"
            },
            "result": {
              "status": "passed",
              "duration": 11900
            }
          }
        ],
        "steps": [
          {
            "keyword": "Given ",
            "name": "that I access the home page",
            "line": 7,
            "match": {
              "location": "features/step_definitions/home/home_steps.rb:1"
            },
            "result": {
              "status": "passed",
              "duration": 13564030900
            }
          },
          {
            "keyword": "And ",
            "name": "I go to the products 'T-Shirts' session",
            "line": 10,
            "match": {
              "location": "features/step_definitions/home/home_steps.rb:5"
            },
            "result": {
              "status": "passed",
              "duration": 892058000
            }
          },
          {
            "keyword": "When ",
            "name": "I add a product to my cart",
            "line": 11,
            "match": {
              "location": "features/step_definitions/category/category_steps.rb:1"
            },
            "result": {
              "status": "passed",
              "duration": 2226524200
            }
          },
          {
            "keyword": "Then ",
            "name": "I should see the product on my cart",
            "line": 12,
            "match": {
              "location": "features/step_definitions/cart/cart_steps.rb:1"
            },
            "result": {
              "status": "passed",
              "duration": 1749007600
            }
          }
        ],
        "after": [
          {
            "match": {
              "location": "capybara-3.29.0/lib/capybara/cucumber.rb:10"
            },
            "result": {
              "status": "passed",
              "duration": 440566600
            }
          }
        ]
      },
      {
        "keyword": "Background",
        "name": "",
        "description": "",
        "line": 6,
        "type": "background",
        "before": [
          {
            "match": {
              "location": "capybara-3.29.0/lib/capybara/cucumber.rb:14"
            },
            "result": {
              "status": "passed",
              "duration": 32400
            }
          },
          {
            "match": {
              "location": "capybara-3.29.0/lib/capybara/cucumber.rb:22"
            },
            "result": {
              "status": "passed",
              "duration": 34500
            }
          },
          {
            "match": {
              "location": "features/support/hooks.rb:1"
            },
            "result": {
              "status": "passed",
              "duration": 17100
            }
          }
        ],
        "steps": [
          {
            "keyword": "Given ",
            "name": "that I access the home page",
            "line": 7,
            "match": {
              "location": "features/step_definitions/home/home_steps.rb:1"
            },
            "result": {
              "status": "passed",
              "duration": 2094629600
            }
          },
          {
            "keyword": "And ",
            "name": "I go to the products 'Dresses' session",
            "line": 10,
            "match": {
              "location": "features/step_definitions/home/home_steps.rb:5"
            },
            "result": {
              "status": "passed",
              "duration": 2162639700
            }
          },
          {
            "keyword": "When ",
            "name": "I add a product to my cart",
            "line": 11,
            "match": {
              "location": "features/step_definitions/category/category_steps.rb:1"
            },
            "result": {
              "status": "passed",
              "duration": 1233857900
            }
          },
          {
            "keyword": "Then ",
            "name": "I should see the product on my cart",
            "line": 12,
            "match": {
              "location": "features/step_definitions/cart/cart_steps.rb:1"
            },
            "result": {
              "status": "passed",
              "duration": 1117791500
            }
          }
        ],
        "after": [
          {
            "match": {
              "location": "capybara-3.29.0/lib/capybara/cucumber.rb:10"
            },
            "result": {
              "status": "passed",
              "duration": 375441400
            }
          }
        ]
      },
      {
        "keyword": "Background",
        "name": "",
        "description": "",
        "line": 6,
        "type": "background",
        "before": [
          {
            "match": {
              "location": "capybara-3.29.0/lib/capybara/cucumber.rb:14"
            },
            "result": {
              "status": "passed",
              "duration": 28500
            }
          },
          {
            "match": {
              "location": "capybara-3.29.0/lib/capybara/cucumber.rb:22"
            },
            "result": {
              "status": "passed",
              "duration": 16400
            }
          },
          {
            "match": {
              "location": "features/support/hooks.rb:1"
            },
            "result": {
              "status": "passed",
              "duration": 14200
            }
          }
        ],
        "steps": [
          {
            "keyword": "Given ",
            "name": "that I access the home page",
            "line": 7,
            "match": {
              "location": "features/step_definitions/home/home_steps.rb:1"
            },
            "result": {
              "status": "passed",
              "duration": 1584580300
            }
          },
          {
            "keyword": "And ",
            "name": "I go to the products 'Women' session",
            "line": 10,
            "match": {
              "location": "features/step_definitions/home/home_steps.rb:5"
            },
            "result": {
              "status": "passed",
              "duration": 1985575100
            }
          },
          {
            "keyword": "When ",
            "name": "I add a product to my cart",
            "line": 11,
            "match": {
              "location": "features/step_definitions/category/category_steps.rb:1"
            },
            "result": {
              "status": "passed",
              "duration": 1239561000
            }
          },
          {
            "keyword": "Then ",
            "name": "I should see the product on my cart",
            "line": 12,
            "match": {
              "location": "features/step_definitions/cart/cart_steps.rb:1"
            },
            "result": {
              "status": "passed",
              "duration": 1144371800
            }
          }
        ],
        "after": [
          {
            "match": {
              "location": "capybara-3.29.0/lib/capybara/cucumber.rb:10"
            },
            "result": {
              "status": "passed",
              "duration": 376624700
            }
          }
        ]
      }
    ]
  }
]